sparqly/__init__.py
sparqly/item.py
sparqly/query.py
sparqly/sanitizer.py
sparqly-0.1.1.dist-info/LICENSE
sparqly-0.1.1.dist-info/METADATA
sparqly-0.1.1.dist-info/WHEEL
sparqly-0.1.1.dist-info/top_level.txt
sparqly-0.1.1.dist-info/RECORD
