Metadata-Version: 2.1
Name: sparqly
Version: 0.1.1
Summary: SPARQL semantic translator and ORM for Python.
Home-page: https://github.com/Dustpancake/sparqly
Author: Dustpancake
Author-email: fergusb.temp@gmail.com
License: UNKNOWN
Platform: UNKNOWN
Classifier: Programming Language :: Python :: 3.7
Classifier: License :: OSI Approved :: GNU General Public License v3 (GPLv3)
Requires-Python: >=3.7
